mixiu_app_helper/__init__.py
mixiu_app_helper/info.py
mixiu_app_helper/api/__init__.py
mixiu_app_helper/api/my.py
mixiu_app_helper/api/http/__init__.py
mixiu_app_helper/api/http/auth.py
mixiu_app_helper/api/http/g.py
mixiu_app_helper/api/http/gift.py
mixiu_app_helper/api/http/global.py
mixiu_app_helper/api/http/http_client.py
mixiu_app_helper/api/http/im.py
mixiu_app_helper/api/http/live.py
mixiu_app_helper/api/http/maintain.py
mixiu_app_helper/api/http/music.py
mixiu_app_helper/api/http/play_with.py
mixiu_app_helper/api/http/product_manager.py
mixiu_app_helper/api/http/public_resource.py
mixiu_app_helper/api/http/redpack.py
mixiu_app_helper/api/http/relation.py
mixiu_app_helper/api/http/resource.py
mixiu_app_helper/api/http/room.py
mixiu_app_helper/api/http/square.py
mixiu_app_helper/api/http/task.py
mixiu_app_helper/api/http/tour.py
mixiu_app_helper/api/http/user.py
mixiu_app_helper/api/http/voice.py
mixiu_app_helper/api/page/__init__.py
mixiu_app_helper/api/page/chat.py
mixiu_app_helper/api/page/emoji.py
mixiu_app_helper/api/page/portal.py
mixiu_app_helper/api/page/home/__init__.py
mixiu_app_helper/api/page/home/favorite.py
mixiu_app_helper/api/page/home/home.py
mixiu_app_helper/api/page/home/live.py
mixiu_app_helper/api/page/home/room.py
mixiu_app_helper/api/page/home/video.py
mixiu_app_helper/api/page/home/voice.py
mixiu_app_helper/api/page/my/__init__.py
mixiu_app_helper/api/page/my/my.py
mixiu_app_helper/api/page/my/profile.py
mixiu_app_helper/api/page/my/settings.py
mixiu_app_helper/api/page/popup/__init__.py
mixiu_app_helper/api/page/popup/gift.py
mixiu_app_helper-0.2.4.dist-info/LICENSE
mixiu_app_helper-0.2.4.dist-info/METADATA
mixiu_app_helper-0.2.4.dist-info/WHEEL
mixiu_app_helper-0.2.4.dist-info/top_level.txt
mixiu_app_helper-0.2.4.dist-info/RECORD
