Metadata-Version: 2.1
Name: mixiu-app-helper
Version: 0.2.4
Summary: This is my mixiu app helper package
Home-page: https://github.com/ckf10000/mixiu-app-helper
Author: ckf10000
Author-email: ckf10000@sina.com
Classifier: Programming Language :: Python :: 3
Classifier: License :: OSI Approved :: MIT License
Classifier: Operating System :: OS Independent
License-File: LICENSE
Requires-Dist: airtest-helper >=0.1.1
